dj_shortwalk/__init__.py
dj_shortwalk/dj_shortwalk.py
djangoshortwalk-1.0.dist-info/LICENSE
djangoshortwalk-1.0.dist-info/METADATA
djangoshortwalk-1.0.dist-info/WHEEL
djangoshortwalk-1.0.dist-info/entry_points.txt
djangoshortwalk-1.0.dist-info/top_level.txt
djangoshortwalk-1.0.dist-info/RECORD
