Metadata-Version: 2.2
Name: djangoshortwalk
Version: 1.0
Summary: For irritated Django developers who type 'python manage.py' too many times...
Home-page: https://github.com/techbipin/dj-shortwalk
Author: Mr. Bipin Rajesh Tatkare
Author-email: techbipinrt2526@gmail.com
Classifier: Development Status :: 5 - Production/Stable
Classifier: Intended Audience :: Developers
Classifier: Natural Language :: English
Classifier: License :: OSI Approved :: MIT License
Classifier: Programming Language :: Python
Classifier: Programming Language :: Python :: 3
Classifier: Programming Language :: Python :: 3.12
Classifier: Operating System :: OS Independent
Requires-Python: >=3.12
License-File: LICENSE
Dynamic: author
Dynamic: author-email
Dynamic: classifier
Dynamic: description
Dynamic: description-content-type
Dynamic: home-page
Dynamic: requires-python
Dynamic: summary
